alpamayo_tools/__init__.py
alpamayo_tools/dataloader.py
alpamayo_tools/embeddings.py
alpamayo_tools/inference.py
alpamayo_tools/cli/__init__.py
alpamayo_tools/cli/generate_labels.py
alpamayo_tools-0.2.0.dist-info/METADATA
alpamayo_tools-0.2.0.dist-info/WHEEL
alpamayo_tools-0.2.0.dist-info/entry_points.txt
alpamayo_tools-0.2.0.dist-info/licenses/LICENSE
alpamayo_tools-0.2.0.dist-info/RECORD
