Metadata-Version: 2.4
Name: alpamayo-tools
Version: 0.2.0
Summary: Community tools for NVIDIA's Alpamayo/PhysicalAI-AV ecosystem
Project-URL: Homepage, https://github.com/mu-hashmi/alpamayo-tools
Project-URL: Documentation, https://github.com/mu-hashmi/alpamayo-tools#readme
Project-URL: Repository, https://github.com/mu-hashmi/alpamayo-tools
Author: Community Contributors
License-Expression: MIT
License-File: LICENSE
Keywords: alpamayo,autonomous-driving,nvidia,pytorch,vla
Classifier: Development Status :: 3 - Alpha
Classifier: Intended Audience :: Science/Research
Classifier: License :: OSI Approved :: MIT License
Classifier: Programming Language :: Python :: 3
Classifier: Programming Language :: Python :: 3.12
Classifier: Programming Language :: Python :: 3.13
Classifier: Topic :: Scientific/Engineering :: Artificial Intelligence
Requires-Python: >=3.12
Requires-Dist: av>=14.0
Requires-Dist: einops>=0.7
Requires-Dist: huggingface-hub>=0.20
Requires-Dist: numpy>=1.24
Requires-Dist: pandas>=2.0
Requires-Dist: physical-ai-av>=0.1.0
Requires-Dist: pyarrow>=15.0
Requires-Dist: scipy>=1.10
Requires-Dist: torch>=2.0
Requires-Dist: tqdm>=4.65
Provides-Extra: all
Requires-Dist: accelerate>=1.0; extra == 'all'
Requires-Dist: hydra-core>=1.3; extra == 'all'
Requires-Dist: omegaconf>=2.3; extra == 'all'
Requires-Dist: sentence-transformers>=2.2; extra == 'all'
Requires-Dist: transformers>=4.45; extra == 'all'
Provides-Extra: dev
Requires-Dist: ipykernel>=7.0; extra == 'dev'
Requires-Dist: pytest-mock>=3.10; extra == 'dev'
Requires-Dist: pytest>=7.0; extra == 'dev'
Provides-Extra: embeddings
Requires-Dist: sentence-transformers>=2.2; extra == 'embeddings'
Provides-Extra: inference
Requires-Dist: accelerate>=1.0; extra == 'inference'
Requires-Dist: hydra-core>=1.3; extra == 'inference'
Requires-Dist: omegaconf>=2.3; extra == 'inference'
Requires-Dist: transformers>=4.45; extra == 'inference'
